sqlt/__init__.py
sqlu/__init__.py
sqlu-0.1.1.dist-info/LICENSE
sqlu-0.1.1.dist-info/METADATA
sqlu-0.1.1.dist-info/WHEEL
sqlu-0.1.1.dist-info/top_level.txt
sqlu-0.1.1.dist-info/RECORD
